{"id":"7598","name":"Dye-Ready Top Hat with Feather","transitionsToward":[{"actorID":"2178","targetID":"2914","newTargetID":"7598","hand":true},{"actorID":"7599","targetID":"731","newActorID":"7598","newTargetID":"731","targetRemains":true,"hand":true}],"transitionsAway":[{"actorID":"7598","targetID":"733","newActorID":"7597","newTargetID":"733","targetRemains":true,"hand":true},{"actorID":"7598","targetID":"734","newActorID":"7595","newTargetID":"734","targetRemains":true,"hand":true},{"actorID":"7598","targetID":"2897","newActorID":"7601","newTargetID":"2897","targetRemains":true,"hand":true},{"actorID":"7598","targetID":"2898","newActorID":"7600","newTargetID":"2898","targetRemains":true,"hand":true},{"actorID":"7598","targetID":"2896","newActorID":"7596","newTargetID":"2896","targetRemains":true,"hand":true}],"transitionsTimed":[{"targetID":"7598","newTargetID":"7599","decay":"5m"}],"version":20272,"craftable":true,"depth":68,"size":2,"minPickupAge":3,"sounds":["941","286"],"techTree":[{"id":"2178","nodes":[{"id":"2177","nodes":[{"id":"2176","nodes":[]}]}]},{"id":"2914","nodes":[{"id":"2885","nodes":[{"id":"192","nodes":[]},{"id":"2889","nodes":[]}]},{"id":"731","nodes":[{"id":"729","nodes":null},{"id":"730","nodes":[]}]}]}],"recipe":{"steps":[[{"id":"8821","count":2,"uses":"x2","mainBranch":true,"depth":6,"actorID":"11660","targetID":"8819","hand":true}],[{"id":"8822","count":2,"uses":"x2","mainBranch":true,"depth":5,"targetID":"8821","hand":true}],[{"id":"2888","count":2,"uses":"x2","mainBranch":true,"depth":4,"actorID":"191","targetID":"8822","hand":true}],[{"id":"2889","mainBranch":true,"depth":3,"actorID":"2888","targetID":"2888","hand":true},{"id":"192","depth":3,"subSteps":[[{"id":"57","count":2,"uses":"x2","depth":5,"targetID":"50","hand":true}],[{"id":"58","depth":4,"actorID":"57","targetID":"57","hand":true}],[{"id":"192","depth":3,"actorID":"191","targetID":"58","hand":true}]]}],[{"id":"2885","mainBranch":true,"depth":2,"actorID":"192","targetID":"2889","hand":true}],[{"id":"2914","mainBranch":true,"depth":1,"actorID":"2885","targetID":"731","hand":true},{"id":"2178","depth":1,"targetID":"2177","hand":true}],[{"id":"7598","mainBranch":true,"depth":0,"actorID":"2178","targetID":"2914","hand":true}]],"ingredients":["11660","191","731","2177","50","50","8819","8819"]}}